plain/support/CHANGELOG.md
plain/support/README.md
plain/support/__init__.py
plain/support/admin.py
plain/support/config.py
plain/support/default_settings.py
plain/support/forms.py
plain/support/models.py
plain/support/urls.py
plain/support/views.py
plain/support/assets/support/embed.js
plain/support/assets/support/iframe.js
plain/support/migrations/0001_initial.py
plain/support/migrations/0002_remove_supportformentry_plainsupport_supportformentry_unique_uuid_and_more.py
plain/support/migrations/__init__.py
plain/support/templates/email/support_form_entry.html
plain/support/templates/support/card.html
plain/support/templates/support/iframe.html
plain/support/templates/support/page.html
plain/support/templates/support/forms/default.html
plain/support/templates/support/success/default.html
plain_support-0.27.1.dist-info/METADATA
plain_support-0.27.1.dist-info/WHEEL
plain_support-0.27.1.dist-info/licenses/LICENSE
plain_support-0.27.1.dist-info/RECORD
