Metadata-Version: 2.4
Name: plain.support
Version: 0.27.1
Summary: Provides support forms for your application.
Author-email: Dave Gaeddert <dave.gaeddert@dropseed.dev>
License-Expression: BSD-3-Clause
License-File: LICENSE
Requires-Python: >=3.13
Requires-Dist: plain-auth<1.0.0
Requires-Dist: plain-models<1.0.0
Requires-Dist: plain<1.0.0
